tvdenoising/__init__.py
tvdenoising/_tv_1d.cpython-310-x86_64-linux-gnu.so
tvdenoising-0.0.1.dist-info/METADATA
tvdenoising-0.0.1.dist-info/LICENSE.txt
tvdenoising-0.0.1.dist-info/WHEEL
tvdenoising-0.0.1.dist-info/top_level.txt
tvdenoising-0.0.1.dist-info/RECORD
