Metadata-Version: 2.1
Name: tvdenoising
Version: 0.0.1
Summary: 1D total variation denoising
Author: The tvdenoising authors
License: zlib
Classifier: Development Status :: 4 - Beta
Classifier: License :: OSI Approved :: zlib/libpng License
Classifier: Programming Language :: Python :: 3
Requires-Python: >=3.8
License-File: LICENSE.txt
Requires-Dist: numpy
